{
  "son_guncelleme": "2026-04-13T16:45:54.686092",
  "not": "SWING TRADE SADECE SİMÜLASYON - Sadece % kazanç/kayıp takibi (MAX: 8 pozisyon)",
  "aktif_pozisyonlar": [
    {
      "id": "SWING-202604101410-CAT",
      "sembol": "CAT",
      "adet": 4,
      "giris_fiyat": 790.66,
      "giris_tarihi": "2026-04-10",
      "stop_loss": 730.35,
      "hedef_fiyat": 941.43,
      "rr_oran": 2.5,
      "tarama_yontemi": "tenkan_bounce, sma50_bounce, kijun_bounce_v2, nr7_sikisma",
      "giris_nedeni": "Seans içi otomatik giriş — tenkan_bounce, sma50_bounce, kijun_bounce_v2, nr7_sikisma",
      "katalizor": "",
      "max_sure_gun": 15,
      "durum": "AKTIF",
      "guncel_fiyat": 788.87,
      "son_fiyat": 788.87,
      "zirve_fiyat": 798.54,
      "chandelier_stop": 713.01,
      "k11_aktif": false,
      "k11_profit_lock": null,
      "son_guncelleme": "2026-04-13",
      "notlar": [
        "Tarih düzeltmesi: 11 Nisan Cumartesi piyasa kapalı — 10 Nisan Cuma kapanış fiyatına göre düzeltildi"
      ],
      "pnl_pct": -0.23,
      "atr14": 25.88,
      "chandelier_guncelleme": "2026-04-10",
      "maliyet_baz": 790.66
    },
    {
      "id": "SWING-202604101410-KLAC",
      "sembol": "KLAC",
      "adet": 1,
      "giris_fiyat": 1737.28,
      "giris_tarihi": "2026-04-10",
      "stop_loss": 1540.49,
      "hedef_fiyat": 2229.26,
      "rr_oran": 2.5,
      "tarama_yontemi": "tenkan_bounce, kijun_bounce_v2",
      "giris_nedeni": "Seans içi otomatik giriş — tenkan_bounce, kijun_bounce_v2",
      "katalizor": "",
      "max_sure_gun": 15,
      "durum": "AKTIF",
      "guncel_fiyat": 1745.04,
      "son_fiyat": 1745.04,
      "zirve_fiyat": 1748.74,
      "chandelier_stop": 1530.73,
      "k11_aktif": false,
      "k11_profit_lock": null,
      "son_guncelleme": "2026-04-13",
      "notlar": [
        "Tarih düzeltmesi: 11 Nisan Cumartesi piyasa kapalı — 10 Nisan Cuma kapanış fiyatına göre düzeltildi"
      ],
      "pnl_pct": 0.45,
      "atr14": 68.85,
      "chandelier_guncelleme": "2026-04-10",
      "maliyet_baz": 1737.28
    },
    {
      "id": "SWING-202604101410-AMAT",
      "sembol": "AMAT",
      "adet": 6,
      "giris_fiyat": 399.49,
      "giris_tarihi": "2026-04-10",
      "stop_loss": 361.98,
      "hedef_fiyat": 493.26,
      "rr_oran": 2.5,
      "tarama_yontemi": "sma50_bounce",
      "giris_nedeni": "Seans içi otomatik giriş — sma50_bounce",
      "katalizor": "",
      "max_sure_gun": 15,
      "durum": "AKTIF",
      "guncel_fiyat": 391.44,
      "son_fiyat": 391.44,
      "zirve_fiyat": 399.49,
      "chandelier_stop": 349.41,
      "k11_aktif": false,
      "k11_profit_lock": null,
      "son_guncelleme": "2026-04-13",
      "notlar": [
        "Tarih düzeltmesi: 11 Nisan Cumartesi piyasa kapalı — 10 Nisan Cuma kapanış fiyatına göre düzeltildi"
      ],
      "pnl_pct": -2.02,
      "atr14": 16.69,
      "chandelier_guncelleme": "2026-04-10",
      "maliyet_baz": 399.49
    }
  ],
  "ozet": {
    "toplam_pozisyon": 3,
    "bos_slot": 5,
    "maksimum_pozisyon": 8,
    "ortalama_kar_zarar_yuzde": 0.0
  }
}