{
  "portfoy_adi": "Agresif Büyüme",
  "max_pozisyon": 6,
  "strateji": {
    "isim": "Agresif Momentum - Aylık %5",
    "aylik_hedef_yuzde": 5.0,
    "max_esanli_pozisyon": 6,
    "pozisyon_buyuklugu_yuzde": "10-15",
    "ortalama_tutma_gun": "3-7",
    "max_tutma_gun": 10,
    "stop_loss_yuzde": 4.0,
    "kar_hedefi_yuzde": "8-12",
    "min_rr_orani": "2:1",
    "min_win_rate_yuzde": 55,
    "aylik_max_drawdown_yuzde": 8.0,
    "gunluk_max_kayip_yuzde": 2.0,
    "haftalik_max_kayip_yuzde": 4.0,
    "sinyal_tipleri": [
      "earnings_momentum",
      "breakout",
      "mean_reversion"
    ],
    "baslangic_tarihi": "2026-02-26",
    "dokuman": "docs/AGGRESSIVE_MOMENTUM_STRATEGY.md",
    "sermaye": 400000,
    "sermaye_degisiklik_tarihi": "2026-02-26",
    "sermaye_notu": "$100K → $400K sermaye artırımı. $300K yeni nakit eklendi."
  },
  "baslangic_sermaye": 400000,
  "nakit": {
    "miktar": 186719.6,
    "para_birimi": "USD",
    "agirlik_yuzde": 37.93
  },
  "pozisyonlar": [
    {
      "sembol": "COHR",
      "isim": "Coherent Corp",
      "sektor": "AI Optik / Yarı İletken",
      "adet": 139,
      "maliyet_baz": 285.7482,
      "yatirim": 39719.0,
      "guncel_fiyat": 343.79,
      "guncel_deger": 47786.81,
      "kar_zarar": 8067.81,
      "kar_zarar_yuzde": 20.31,
      "gunluk_degisim_yuzde": -1.07,
      "agirlik_yuzde": 12.5,
      "son_guncelleme": "2026-04-21T21:13:43.770490",
      "giris_tarihi": "2026-04-10",
      "giris_fiyati": 285.0,
      "giris_nedeni": "Agresif v2 AI optical supply chain. Ichimoku 3/4, RSI 62.8, SMA200 +72%. Gün içi limit 285 doldu (gün dibi 275.69). Stop 265, hedef 330.",
      "cb_kaynak": "kayit-yok",
      "hedef_fiyat": 330.0,
      "stop_loss": 285.75,
      "zirve_fiyat": 347.51,
      "stop_faz": 3,
      "stop_mesafe_pct": 16.88,
      "stop_aciklama": "break-even stop — yüksek ATR (22.92), SMA20 çok uzak, maliyet koruması",
      "stop_guncelleme": "2026-04-10T18:47:48",
      "durum": "🚀 Güçlü (+20.3%)"
    },
    {
      "sembol": "ANET",
      "isim": "Arista Networks",
      "sektor": "AI Networking / Switching",
      "adet": 271,
      "maliyet_baz": 146.5,
      "yatirim": 39701.5,
      "guncel_fiyat": 172.86,
      "guncel_deger": 46845.06,
      "kar_zarar": 7143.56,
      "kar_zarar_yuzde": 17.99,
      "gunluk_degisim_yuzde": 3.6,
      "agirlik_yuzde": 12.25,
      "son_guncelleme": "2026-04-21T21:13:43.770490",
      "giris_tarihi": "2026-04-10",
      "giris_fiyati": 146.5,
      "giris_nedeni": "Agresif v2 AI networking altyapısı. RSI 63.6, SMA20/50/200 üstü. Ichimoku 2/4, kumo üstü. %10.4 aylık RS. Stop 136, hedef 165.",
      "cb_kaynak": "kayit-yok",
      "hedef_fiyat": 165.0,
      "stop_loss": 150.77,
      "zirve_fiyat": 172.86,
      "stop_faz": 3,
      "stop_mesafe_pct": 12.78,
      "stop_aciklama": "2xATR (134.73) + SMA50 (134.43) confluence — anlamlı teknik seviye",
      "stop_guncelleme": "2026-04-10T18:47:48",
      "durum": "✅ Normal"
    },
    {
      "sembol": "MU",
      "isim": "Micron Technology",
      "sektor": "AI Bellek / DRAM",
      "adet": 95,
      "maliyet_baz": 415.0,
      "yatirim": 39425.0,
      "guncel_fiyat": 449.38,
      "guncel_deger": 42691.1,
      "kar_zarar": 3266.1,
      "kar_zarar_yuzde": 8.28,
      "gunluk_degisim_yuzde": 0.21,
      "agirlik_yuzde": 11.17,
      "son_guncelleme": "2026-04-21T21:13:43.770490",
      "giris_tarihi": "2026-04-10",
      "giris_fiyati": 415.0,
      "giris_nedeni": "Agresif v2 AI bellek teması. RSI 54.5 giriş zonu. SMA50/200 üstü. HBM talebi ivmeleniyor. Stop 385, hedef 470.",
      "cb_kaynak": "kayit-yok",
      "hedef_fiyat": 470.0,
      "stop_loss": 415.0,
      "zirve_fiyat": 465.66,
      "stop_faz": 3,
      "stop_mesafe_pct": 7.65,
      "stop_aciklama": "SMA50 teknik destek — altı = trend bozulması",
      "stop_guncelleme": "2026-04-10T18:47:48",
      "durum": "✅ Normal"
    },
    {
      "sembol": "CAMT",
      "isim": "Camtek Ltd",
      "sektor": "Yarı İletken Ekipman / Inspection",
      "adet": 226,
      "maliyet_baz": 175.0,
      "yatirim": 39550.0,
      "guncel_fiyat": 187.71,
      "guncel_deger": 42422.46,
      "kar_zarar": 2872.46,
      "kar_zarar_yuzde": 7.26,
      "gunluk_degisim_yuzde": 1.67,
      "agirlik_yuzde": 11.1,
      "son_guncelleme": "2026-04-21T21:13:43.770490",
      "giris_tarihi": "2026-04-10",
      "giris_fiyati": 175.0,
      "giris_nedeni": "Agresif v2 yarı iletken ekipman teması. RSI 60, SMA20/50 üstü, +17% aylık RS. AI chip üretimi inspection kritik darboğaz. Limit 175 doldu (gün dibi 174.12). Stop 163, hedef 210.",
      "cb_kaynak": "kayit-yok",
      "hedef_fiyat": 210.0,
      "stop_loss": 175.0,
      "zirve_fiyat": 187.71,
      "stop_faz": 2,
      "stop_mesafe_pct": 6.77,
      "stop_aciklama": "SMA20 teknik destek — pozisyon maliyet altında, dikkat",
      "stop_guncelleme": "2026-04-10T18:47:48",
      "durum": "✅ Normal"
    },
    {
      "sembol": "ETN",
      "isim": "Eaton Corporation plc",
      "sektor": "Industrials",
      "adet": 36,
      "maliyet_baz": 406.385,
      "giris_fiyati": 406.385,
      "guncel_fiyat": 409.7,
      "yatirim": 14629.86,
      "guncel_deger": 14749.2,
      "kar_zarar": 119.34,
      "kar_zarar_yuzde": 0.82,
      "gunluk_degisim_yuzde": 0.52,
      "agirlik_yuzde": 3.86,
      "giris_tarihi": "2026-04-20",
      "stop_loss": 382.78,
      "hedef_fiyat": 457.49,
      "tema": "AI_altyapı",
      "giris_nedeni": "AI_altyapı teması — teknik:5/10 fundamental:5/10 valuation:3.8/10",
      "son_guncelleme": "2026-04-21T21:13:43.770490",
      "cb_kaynak": "transactions-2026-04-20",
      "stop_faz": 1,
      "zirve_fiyat": 409.7,
      "stop_mesafe_pct": 6.57,
      "durum": "✅ Normal"
    }
  ],
  "son_guncelleme": "2026-04-22T18:17:57.534495+03:00",
  "toplam_deger": 382315.71,
  "toplam_getiri_yuzde": -4.42,
  "toplam_getiri": -17684.29,
  "_sema_versiyonu": "2026-04-17"
}