{
  "tarih": "2026-05-12T16:02:51.053418+03:00",
  "vix": 18.67,
  "sektor_performans": {
    "Basic Materials": 1.9204965235012805,
    "Communication Services": -1.177271248050027,
    "Consumer Cyclical": 1.4933173189642934,
    "Consumer Defensive": -1.0397928955325098,
    "Energy": 2.3755945202041495,
    "Financial Services": 0.047903509406643785,
    "Healthcare": -1.36118808260709,
    "Industrials": 0.8489149980683397,
    "Real Estate": 0.9693766137897297,
    "Technology": 1.0410287139578145,
    "Utilities": -2.566140243510062
  },
  "dominant_temalar": [
    {
      "tema_adi": "enerji_geçiş",
      "güç_skoru": 9,
      "neden": "Enerji sektörü %2.4 ile en güçlü performansı gösterdi ve İran savaşının enerji fiyatlarını artırması enflasyonu 3.8%'e çıkardı. [KESİN]",
      "öncelikli_alt_dal": "güç_altyapısı",
      "önerilen_hisseler": [
        "VRT",
        "ETN",
        "PWR"
      ],
      "portföy": "aggressive",
      "aciliyet": "yüksek",
      "hisse_evreni": [
        "CEG",
        "WMB",
        "FSLR",
        "NEE",
        "ENPH",
        "OKE",
        "NRG",
        "RUN",
        "VST",
        "ET",
        "KMI",
        "CCJ"
      ]
    },
    {
      "tema_adi": "emtia_kaynak",
      "güç_skoru": 8,
      "neden": "Hammaddeler sektörü %1.9 artışla ikinci sırada yer aldı ve enflasyonist ortamda emtialar güvenli liman olarak öne çıkıyor. [KESİN]",
      "öncelikli_alt_dal": "nadir_toprak",
      "önerilen_hisseler": [
        "MP",
        "CCJ",
        "FCX"
      ],
      "portföy": "aggressive",
      "aciliyet": "yüksek",
      "hisse_evreni": [
        "MP",
        "NOVN",
        "USA"
      ]
    },
    {
      "tema_adi": "savunma_uzay",
      "güç_skoru": 7,
      "neden": "İran savaşı jeopolitik gerilimi artırıyor ve savunma harcamaları beklentilerini güçlendiriyor. [MUHTEMEL]",
      "öncelikli_alt_dal": "hipersonik",
      "önerilen_hisseler": [
        "RTX",
        "LMT",
        "NOC"
      ],
      "portföy": "balanced",
      "aciliyet": "orta",
      "hisse_evreni": [
        "CRWD",
        "LMT",
        "RKLB",
        "ZS",
        "KTOS",
        "PANW",
        "LHX",
        "RDW",
        "RTX",
        "AJRD",
        "S",
        "GD",
        "NOC"
      ]
    }
  ],
  "kacınılacak": [
    "Consumer Defensive",
    "Real Estate"
  ],
  "piyasa_modu": "risk-on",
  "aktif_kriz": {
    "tip": "enflasyon",
    "guven": 8,
    "kanit": "Nisan enflasyonu 3.8%'e çıktı ve haberlerde İran savaşının enerji fiyatlarını artırdığı belirtildi. Enerji sektörü %2.4, Hammaddeler %1.9 artışla öne çıkarken Savunma tüketimi -%1.0 ile geriledi. [KESİN]",
    "beneficiary_sectors": [
      "Energy",
      "Basic Materials",
      "Gold"
    ],
    "sensitive_sectors": [
      "Consumer Defensive",
      "Technology",
      "Consumer Cyclical",
      "Financial Services",
      "Healthcare",
      "Industrials"
    ]
  },
  "genel_yorum": "Piyasada enflasyonist baskılar öne çıkarken jeopolitik gerilim enerji ve emtia temalarını güçlendiriyor. VIX 18.7 ile risk-on modu devam ediyor ancak sektörel rotasyon belirgin. [KESİN]",
  "haberler": [
    {
      "baslik": "A Buying Opportunity In The Bond Market This Summer",
      "kaynak": "seekingalpha.com",
      "tarih": "2026-05-12 08:52"
    },
    {
      "baslik": "Inflation continued to rise in April as Iran war impacted energy prices",
      "kaynak": "foxbusiness.com",
      "tarih": "2026-05-12 08:51"
    },
    {
      "baslik": "Inflation Approached 3-Year High In April As Energy Prices Soared",
      "kaynak": "forbes.com",
      "tarih": "2026-05-12 08:45"
    },
    {
      "baslik": "US inflation jumped to 3.8% in April as war with Iran continues to drive up prices",
      "kaynak": "theguardian.com",
      "tarih": "2026-05-12 08:37"
    },
    {
      "baslik": "The End Of Long-Term Investing?",
      "kaynak": "seekingalpha.com",
      "tarih": "2026-05-12 08:34"
    }
  ]
}