{
  "son_guncelleme": "2026-02-25",
  "simulasyon_donemi": "17 Şubat 2026 - 25 Şubat 2026",
  "islem_gunleri": 7,
  "toplam_sermaye": 400000.0,
  "toplam_deger": 422466.61,
  "toplam_kar_zarar": 22466.61,
  "toplam_kar_zarar_yuzde": 5.62,
  "benchmark_spy": 0.66,
  "alpha": 4.96,
  "portfolyolar": {
    "dengeli": {
      "isim": "Dengeli Portföy",
      "deger": 108789.71,
      "maliyet": 100000,
      "kar_zarar": 8789.71,
      "kar_zarar_yuzde": 8.79,
      "pozisyon_sayisi": 6,
      "nakit": {
        "miktar": 9613.2,
        "para_birimi": "USD"
      },
      "durum": "BAŞARILI"
    },
    "agresif": {
      "isim": "Agresif Büyüme",
      "deger": 91972.9,
      "maliyet": 100000,
      "kar_zarar": -8027.1,
      "kar_zarar_yuzde": -8.03,
      "pozisyon_sayisi": 9,
      "nakit": {
        "miktar": 19910.71,
        "para_birimi": "USD"
      },
      "durum": "KAYIPLI"
    },
    "temettü": {
      "isim": "Değer + Temettü",
      "deger": 116617.52,
      "maliyet": 100000,
      "kar_zarar": 16617.52,
      "kar_zarar_yuzde": 16.62,
      "pozisyon_sayisi": 7,
      "nakit": {
        "miktar": 648.12,
        "para_birimi": "USD"
      },
      "durum": "BAŞARILI"
    },
    "rotasyon": {
      "isim": "Sektör Rotasyonu",
      "deger": 105086.48,
      "maliyet": 100000,
      "kar_zarar": 5086.48,
      "kar_zarar_yuzde": 5.09,
      "pozisyon_sayisi": 3,
      "nakit": {
        "miktar": 668.0800000000054,
        "para_birimi": "USD"
      },
      "durum": "BAŞARILI"
    },
    "swing_trade": {
      "isim": "Swing Trade (Simülasyon)",
      "pozisyon_sayisi": 8,
      "ortalama_getiri_yuzde": 0.94,
      "bos_slot": 2,
      "durum": "8/10 pozisyon aktif"
    }
  },
  "spy_baslangic_fiyati": 682.85,
  "son_islemler": [
    "[ALIŞ] Agresif - TYL @$323.78 x30 = $9,713.40 - Devlet yazılım + AI moat, Axon paraleli"
  ]
}